pyquadp/__init__.py
pyquadp/constant.py
pyquadp/pyquadp.h
pyquadp/qcmath.py
pyquadp/qcmathc.c
pyquadp/qcmathc.cpython-312-x86_64-linux-musl.so
pyquadp/qcmathc.h
pyquadp/qcmplx.c
pyquadp/qcmplx.h
pyquadp/qfloat.c
pyquadp/qfloat.h
pyquadp/qfloatarray.c
pyquadp/qfloatarray.h
pyquadp/qint.c
pyquadp/qint.h
pyquadp/qmath.py
pyquadp/qmathc.c
pyquadp/qmathc.cpython-312-x86_64-linux-musl.so
pyquadp/qmathc.h
pyquadp/qmcmplx.cpython-312-x86_64-linux-musl.so
pyquadp/qmfloat.cpython-312-x86_64-linux-musl.so
pyquadp/qmint.cpython-312-x86_64-linux-musl.so
pyquadp.libs/libquadmath-bb76a5fc.so.0.0.0
pyquadp-1.0.0.dist-info/METADATA
pyquadp-1.0.0.dist-info/WHEEL
pyquadp-1.0.0.dist-info/top_level.txt
pyquadp-1.0.0.dist-info/RECORD
pyquadp-1.0.0.dist-info/licenses/COPYING.txt
