Metadata-Version: 2.4
Name: pyquadp
Version: 1.0.0
Summary: Python's bindings for gcc's libquadmath
Author-email: Robert Farmer <robert.j.farmer37@gmail.com>
License-Expression: GPL-2.0-or-later
Project-URL: Homepage, https://github.com/rjfarmer/pyquadp
Classifier: Programming Language :: Python :: 3
Classifier: Programming Language :: Python :: 3 :: Only
Classifier: Programming Language :: Python :: 3.10
Classifier: Programming Language :: Python :: 3.11
Classifier: Programming Language :: Python :: 3.12
Classifier: Programming Language :: Python :: 3.13
Classifier: Topic :: Software Development :: Code Generators
Requires-Python: >=3.10
License-File: COPYING.txt
Requires-Dist: numpy
Provides-Extra: test
Requires-Dist: pytest; extra == "test"
Requires-Dist: pytest-xdist[psutil]; extra == "test"
Requires-Dist: hypothesis; extra == "test"
Requires-Dist: scipy; extra == "test"
Provides-Extra: coverage
Requires-Dist: pytest; extra == "coverage"
Requires-Dist: pytest-xdist[psutil]; extra == "coverage"
Requires-Dist: pytest-cov; extra == "coverage"
Requires-Dist: scipy; extra == "coverage"
Provides-Extra: dev
Requires-Dist: pre-commit; extra == "dev"
Requires-Dist: black; extra == "dev"
Requires-Dist: pytest; extra == "dev"
Requires-Dist: pytest-xdist[psutil]; extra == "dev"
Requires-Dist: scipy; extra == "dev"
Provides-Extra: perfomance
Requires-Dist: pytest; extra == "perfomance"
Requires-Dist: pytest-codspeed; extra == "perfomance"
Requires-Dist: pytest-xdist[psutil]; extra == "perfomance"
Requires-Dist: scipy; extra == "perfomance"
Dynamic: license-file
